[
  {
    "source": "한국경제",
    "title": "압구정 3구역 어떻게 바뀔까…현대건설 청사진 '원 시티' 공개",
    "summary": "",
    "published": "Wed, 22 Apr 2026 11:07:59 +0900",
    "link": "https://www.hankyung.com/article/2026042283356"
  },
  {
    "source": "한국경제",
    "title": "결제에서 통화질서까지…스테이블코인 입체 분석 [책마을]",
    "summary": "",
    "published": "Wed, 22 Apr 2026 11:03:30 +0900",
    "link": "https://www.hankyung.com/article/202604178236i"
  },
  {
    "source": "한국경제",
    "title": "언제 이렇게 올랐지…코스닥서 '전기·전자' 업종 비중 1위",
    "summary": "",
    "published": "Wed, 22 Apr 2026 10:58:40 +0900",
    "link": "https://www.hankyung.com/article/202604228363i"
  },
  {
    "source": "매일경제",
    "title": "U.S., Japan press Korea to keep fuel exports flowing as Middle East risk persist",
    "summary": "Major countries, including the United States and Japan, have reportedly asked the South Korean gover..",
    "published": "Wed, 22 Apr 2026 11:19:35 +09:00",
    "link": "https://www.mk.co.kr/news/english/12023865"
  },
  {
    "source": "매일경제",
    "title": "“귀걸이인 줄 알았네”…삼성 차세대 이어버드 디자인 엿보니",
    "summary": "삼성전자가 귀에 거는 ‘클립형’ 디자인의 차세대 무선 이어폰을 개발 중인 것으로 알려졌다. 기존의 커널형(귓구멍 삽입형)이나 오픈형 디자인에서 벗어나 귀 모양에 맞게 끼우는 새로운..",
    "published": "Wed, 22 Apr 2026 11:18:34 +09:00",
    "link": "https://www.mk.co.kr/news/business/12023863"
  },
  {
    "source": "매일경제",
    "title": "젠큐릭스, AACR서 소세포폐암 액체생검 성과 발표… “일치율 80% 입증”",
    "summary": "암 분자진단 전문기업 젠큐릭스는 미국 샌디에이고에서 열린 미국암연구학회(AACR) 2026에서 소세포폐암(SCLC)의 비침습적 분자 아형 분류 연구 결과를 발표했다고 22일 밝혔다..",
    "published": "Wed, 22 Apr 2026 11:17:12 +09:00",
    "link": "https://www.mk.co.kr/news/stock/12023860"
  },
  {
    "source": "연합뉴스",
    "title": "우유자조금관리위, 어르신 우유 지원 협약…공공우유급식 확대 추진",
    "summary": "우유자조금관리위원회, 농협경제지주, 한국유가공협회, 한국노인복지관협회 관계자들이 21일 서울 종로노인복지센터에서 ‘어르신 우유 지원 시범사업’ 상생협약을 체결하고 기념촬영을 하고 있다. 좌측부터 오용관 낙농조합장협의회 협의회장, 김형식 한국노인종합복지관협회 회장, 이승호 우유자조금관리위원회 위원장, 이창범 한국유가공협회 회장 [우유자조금관리위원회 제공]우유",
    "published": "Wed, 22 Apr 2026 11:14:13 +0900",
    "link": "https://www.yonhapnewstv.co.kr/news/AKR20260422111411ZYN"
  },
  {
    "source": "연합뉴스",
    "title": "\"석유 최고가격제, 3월 물가 0.8%p 낮춰\"",
    "summary": "한국개발연구원 KDI는 중동 전쟁에 따른 고유가 대응책으로 시행된 석유 최고가격제가 3월 소비자물가를 최대 0.8%p 낮추는 효과가 있었다고 분석했습니다. KDI는 오늘(22일) 1차 최고가격제가 3월 소비자물가를 0.4~0.8%p 낮춘 것으로 추산된다며 이같이 밝혔습니다. 또 이달부터 본격적으로 반영될 유류세 인하 효과는 소비자물가를 대략 0.2%p 낮출",
    "published": "Wed, 22 Apr 2026 11:08:07 +0900",
    "link": "https://www.yonhapnewstv.co.kr/news/MYH20260422110749OUD"
  },
  {
    "source": "연합뉴스",
    "title": "결혼 성수기 피해 늘어…\"깜깜이 계약 주의해야\"",
    "summary": "봄철 결혼 성수기를 앞두고 정부가 결혼서비스 소비자 피해예방 주의보를 발령했습니다. 공정거래위원회와 한국소비자원에 따르면 결혼서비스 관련 피해구제 신청은 지난해 1,076건으로 전년보다 18.9% 증가했는데, 4, 5월에는 56.0% 늘었습니다. 피해의 88% 이상은 계약 해지와 위약금, 청약철회 관련 분쟁으로, 세부 가격과 추가 비용을 제대로 안내받지 못",
    "published": "Wed, 22 Apr 2026 11:07:22 +0900",
    "link": "https://www.yonhapnewstv.co.kr/news/MYH20260422110703N4z"
  },
  {
    "source": "CNBC",
    "title": "Trump administration discussing currency swap line with United Arab Emirates",
    "summary": "Such a move would provide liquidity in dollars to the oil-rich UAE, but could be politically tenuous for the administration amid higher prices at home.",
    "published": "Tue, 21 Apr 2026 22:09:55 GMT",
    "link": "https://www.cnbc.com/2026/04/21/trump-iran-war-white-house-uae-currency-swap-line.html"
  },
  {
    "source": "CNBC",
    "title": "Volkswagen announces voice AI in its Chinese cars from later this year",
    "summary": "Volkswagen revealed four cars, including the ID. UNYX 09, which the company said it co-developed with EV maker Xpeng in two years.",
    "published": "Tue, 21 Apr 2026 13:36:21 GMT",
    "link": "https://www.cnbc.com/2026/04/21/volkswagen-voice-ai-chinese-cars-automaker.html"
  },
  {
    "source": "CNBC",
    "title": "Here's what to expect from Fed chair nominee Kevin Warsh's Senate hearing Tuesday",
    "summary": "In a much-anticipated hearing before the Banking Committee, the former Fed governor will face questioning over a variety of subjects",
    "published": "Tue, 21 Apr 2026 13:13:52 GMT",
    "link": "https://www.cnbc.com/2026/04/21/kevin-warshs-senate-hearing-what-to-expect.html"
  },
  {
    "source": "MarketWatch",
    "title": "Elon Musk in a post on X says some of his Trump posts ‘went too far’ and that he regrets them",
    "summary": "",
    "published": "Wed, 11 Jun 2025 07:09:00 GMT",
    "link": "https://www.marketwatch.com/story/elon-musk-in-a-post-on-x-says-some-of-his-trump-posts-went-too-far-and-that-he-regrets-them-90e73a6a?mod=mw_rss_realtimeheadlines"
  },
  {
    "source": "MarketWatch",
    "title": "Bank of England decision on Thursday will be at 12:02 p.m. local time instead of 12 p.m., due to VE Day’s two minutes of silence",
    "summary": "",
    "published": "Tue, 06 May 2025 11:59:00 GMT",
    "link": "https://www.marketwatch.com/story/bank-of-england-decision-on-thursday-will-be-at-12-02-p-m-local-time-instead-of-12-p-m-due-to-ve-day-two-minutes-of-silence-1f6bed66?mod=mw_rss_realtimeheadlines"
  },
  {
    "source": "MarketWatch",
    "title": "Swiss National Bank cuts interest rates by a half point to 0.5%",
    "summary": "",
    "published": "Thu, 12 Dec 2024 08:32:00 GMT",
    "link": "https://www.marketwatch.com/story/swiss-national-bank-cuts-interest-rates-by-a-half-point-to-0-5-ed1fce78?mod=mw_rss_realtimeheadlines"
  },
  {
    "source": "Bloomberg",
    "title": "Gold Recovers After Two-Day Drop as Trump Extends Iran Ceasefire",
    "summary": "Gold regained some ground after a two-day decline, as US President Donald Trump extended a ceasefire with Iran and allowed more time to arrange a fresh round of peace talks.",
    "published": "Tue, 21 Apr 2026 22:22:50 GMT",
    "link": "https://www.bloomberg.com/news/articles/2026-04-21/gold-steadies-as-trump-extends-iran-ceasefire-peace-talks-stall"
  },
  {
    "source": "Bloomberg",
    "title": "Memory Stock Valuations Spark Debate Over ‘Supercycle’ Potential",
    "summary": "Memory makers are riding surging demand to record profits, yet their stocks are still trading at a fraction of the valuation multiples of other top artificial intelligence chip names.",
    "published": "Tue, 21 Apr 2026 23:00:00 GMT",
    "link": "https://www.bloomberg.com/news/articles/2026-04-21/memory-stock-valuations-spark-debate-over-supercycle-potential"
  },
  {
    "source": "Bloomberg",
    "title": "BHP Strikes Iron Ore Deal With China After Months of Talks",
    "summary": "BHP Group has struck a supply deal with China’s state-backed iron ore buyer, ending a months-long standoff between a vital consumer and the world’s largest miner that has roiled markets and hampered s",
    "published": "Tue, 21 Apr 2026 22:56:05 GMT",
    "link": "https://www.bloomberg.com/news/articles/2026-04-21/bhp-says-it-has-concluded-iron-ore-sales-negotiations-with-cmrg"
  },
  {
    "source": "Investing_com",
    "title": "Earnings call transcript: Airtasker Q3 2026 reveals strong growth in key markets",
    "summary": "",
    "published": "2026-04-22 02:08:35",
    "link": "https://www.investing.com/news/transcripts/earnings-call-transcript-airtasker-q3-2026-reveals-strong-growth-in-key-markets-93CH-4628014"
  },
  {
    "source": "Investing_com",
    "title": "Earnings call transcript: Hillgrove Resources Q1 2026 sees strong copper production",
    "summary": "",
    "published": "2026-04-22 02:06:26",
    "link": "https://www.investing.com/news/transcripts/earnings-call-transcript-hillgrove-resources-q1-2026-sees-strong-copper-production-93CH-4628013"
  },
  {
    "source": "Investing_com",
    "title": "FAA probes close call between two passenger jets at New York’s JFK airport",
    "summary": "",
    "published": "2026-04-22 02:06:24",
    "link": "https://www.investing.com/news/world-news/faa-probes-close-call-between-two-passenger-jets-at-new-yorks-jfk-airport-4628012"
  },
  {
    "source": "Yahoo_Finance",
    "title": "Major crypto platform shuts down amid market slump",
    "summary": "",
    "published": "2026-04-20T21:50:00Z",
    "link": "https://finance.yahoo.com/markets/crypto/articles/major-crypto-platform-shuts-down-215000383.html"
  },
  {
    "source": "Yahoo_Finance",
    "title": "MongoDB’s (MDB) Long-Term Growth Trajectory Overshadows Guidance Shortfall",
    "summary": "",
    "published": "2026-04-20T14:28:16Z",
    "link": "https://finance.yahoo.com/markets/stocks/articles/mongodb-mdb-long-term-growth-142816160.html"
  },
  {
    "source": "Yahoo_Finance",
    "title": "Here’s What Positioned Repligen Corporation (RGEN) for a Durable Long-Term Growth",
    "summary": "",
    "published": "2026-04-20T14:30:35Z",
    "link": "https://finance.yahoo.com/markets/stocks/articles/positioned-repligen-corporation-rgen-durable-143035281.html"
  }
]