[
  {
    "regime": "강세",
    "score": 10,
    "strategy": "강세장_전략",
    "kospi_current": 6475.63,
    "kospi_ma20": 5856.84,
    "kospi_drawdown": -0.0,
    "week_change": 4.13,
    "month_change": 22.71,
    "consecutive_days": 187,
    "details": [
      "✅ 코스피 단기 정배열",
      "✅ 코스피 장기 정배열",
      "✅ 코스피 20일선 위",
      "✅ 최근 5일 +4.1% 상승",
      "✅ 최근 20일 +22.7% 상승",
      "✅ VIX 낮음 (19.1) → 안정",
      "✅ 고점 대비 -0.0% (건강한 상승)"
    ],
    "prev_regime": "강세",
    "regime_changed": false,
    "updated": "2026-04-24T22:10:16.253533"
  },
  {
    "regime": "강세",
    "score": 10,
    "strategy": "강세장_전략",
    "kospi_current": 6475.63,
    "kospi_ma20": 5856.84,
    "kospi_drawdown": -0.0,
    "week_change": 4.13,
    "month_change": 22.71,
    "consecutive_days": 188,
    "details": [
      "✅ 코스피 단기 정배열",
      "✅ 코스피 장기 정배열",
      "✅ 코스피 20일선 위",
      "✅ 최근 5일 +4.1% 상승",
      "✅ 최근 20일 +22.7% 상승",
      "✅ VIX 낮음 (18.9) → 안정",
      "✅ 고점 대비 -0.0% (건강한 상승)"
    ],
    "prev_regime": "강세",
    "regime_changed": false,
    "updated": "2026-04-24T22:41:10.846311"
  },
  {
    "regime": "강세",
    "score": 10,
    "strategy": "강세장_전략",
    "kospi_current": 6475.63,
    "kospi_ma20": 5856.84,
    "kospi_drawdown": -0.0,
    "week_change": 4.13,
    "month_change": 22.71,
    "consecutive_days": 189,
    "details": [
      "✅ 코스피 단기 정배열",
      "✅ 코스피 장기 정배열",
      "✅ 코스피 20일선 위",
      "✅ 최근 5일 +4.1% 상승",
      "✅ 최근 20일 +22.7% 상승",
      "✅ VIX 낮음 (19.4) → 안정",
      "✅ 고점 대비 -0.0% (건강한 상승)"
    ],
    "prev_regime": "강세",
    "regime_changed": false,
    "updated": "2026-04-24T23:12:02.323461"
  },
  {
    "regime": "강세",
    "score": 10,
    "strategy": "강세장_전략",
    "kospi_current": 6475.63,
    "kospi_ma20": 5856.84,
    "kospi_drawdown": -0.0,
    "week_change": 4.13,
    "month_change": 22.71,
    "consecutive_days": 190,
    "details": [
      "✅ 코스피 단기 정배열",
      "✅ 코스피 장기 정배열",
      "✅ 코스피 20일선 위",
      "✅ 최근 5일 +4.1% 상승",
      "✅ 최근 20일 +22.7% 상승",
      "✅ VIX 낮음 (18.9) → 안정",
      "✅ 고점 대비 -0.0% (건강한 상승)"
    ],
    "prev_regime": "강세",
    "regime_changed": false,
    "updated": "2026-04-24T23:42:51.288931"
  },
  {
    "regime": "강세",
    "score": 10,
    "strategy": "강세장_전략",
    "kospi_current": 6475.81,
    "kospi_ma20": 5805.0,
    "kospi_drawdown": 0.0,
    "week_change": 4.58,
    "month_change": 19.07,
    "consecutive_days": 191,
    "details": [
      "✅ 코스피 단기 정배열",
      "✅ 코스피 장기 정배열",
      "✅ 코스피 20일선 위",
      "✅ 최근 5일 +4.6% 상승",
      "✅ 최근 20일 +19.1% 상승",
      "✅ VIX 낮음 (18.7) → 안정",
      "✅ 고점 대비 0.0% (건강한 상승)"
    ],
    "prev_regime": "강세",
    "regime_changed": false,
    "updated": "2026-04-25T00:13:40.784133"
  },
  {
    "regime": "강세",
    "score": 10,
    "strategy": "강세장_전략",
    "kospi_current": 6475.81,
    "kospi_ma20": 5805.0,
    "kospi_drawdown": 0.0,
    "week_change": 4.58,
    "month_change": 19.07,
    "consecutive_days": 192,
    "details": [
      "✅ 코스피 단기 정배열",
      "✅ 코스피 장기 정배열",
      "✅ 코스피 20일선 위",
      "✅ 최근 5일 +4.6% 상승",
      "✅ 최근 20일 +19.1% 상승",
      "✅ VIX 낮음 (18.7) → 안정",
      "✅ 고점 대비 0.0% (건강한 상승)"
    ],
    "prev_regime": "강세",
    "regime_changed": false,
    "updated": "2026-04-25T00:44:36.579337"
  },
  {
    "regime": "강세",
    "score": 10,
    "strategy": "강세장_전략",
    "kospi_current": 6475.81,
    "kospi_ma20": 5805.0,
    "kospi_drawdown": 0.0,
    "week_change": 4.58,
    "month_change": 19.07,
    "consecutive_days": 193,
    "details": [
      "✅ 코스피 단기 정배열",
      "✅ 코스피 장기 정배열",
      "✅ 코스피 20일선 위",
      "✅ 최근 5일 +4.6% 상승",
      "✅ 최근 20일 +19.1% 상승",
      "✅ VIX 낮음 (18.6) → 안정",
      "✅ 고점 대비 0.0% (건강한 상승)"
    ],
    "prev_regime": "강세",
    "regime_changed": false,
    "updated": "2026-04-25T01:15:25.971815"
  },
  {
    "regime": "강세",
    "score": 10,
    "strategy": "강세장_전략",
    "kospi_current": 6475.81,
    "kospi_ma20": 5805.0,
    "kospi_drawdown": 0.0,
    "week_change": 4.58,
    "month_change": 19.07,
    "consecutive_days": 194,
    "details": [
      "✅ 코스피 단기 정배열",
      "✅ 코스피 장기 정배열",
      "✅ 코스피 20일선 위",
      "✅ 최근 5일 +4.6% 상승",
      "✅ 최근 20일 +19.1% 상승",
      "✅ VIX 낮음 (18.7) → 안정",
      "✅ 고점 대비 0.0% (건강한 상승)"
    ],
    "prev_regime": "강세",
    "regime_changed": false,
    "updated": "2026-04-25T01:46:20.657673"
  },
  {
    "regime": "강세",
    "score": 10,
    "strategy": "강세장_전략",
    "kospi_current": 6475.81,
    "kospi_ma20": 5805.0,
    "kospi_drawdown": 0.0,
    "week_change": 4.58,
    "month_change": 19.07,
    "consecutive_days": 195,
    "details": [
      "✅ 코스피 단기 정배열",
      "✅ 코스피 장기 정배열",
      "✅ 코스피 20일선 위",
      "✅ 최근 5일 +4.6% 상승",
      "✅ 최근 20일 +19.1% 상승",
      "✅ VIX 낮음 (18.7) → 안정",
      "✅ 고점 대비 0.0% (건강한 상승)"
    ],
    "prev_regime": "강세",
    "regime_changed": false,
    "updated": "2026-04-25T02:17:10.093388"
  },
  {
    "regime": "강세",
    "score": 10,
    "strategy": "강세장_전략",
    "kospi_current": 6475.81,
    "kospi_ma20": 5805.0,
    "kospi_drawdown": 0.0,
    "week_change": 4.58,
    "month_change": 19.07,
    "consecutive_days": 196,
    "details": [
      "✅ 코스피 단기 정배열",
      "✅ 코스피 장기 정배열",
      "✅ 코스피 20일선 위",
      "✅ 최근 5일 +4.6% 상승",
      "✅ 최근 20일 +19.1% 상승",
      "✅ VIX 낮음 (18.8) → 안정",
      "✅ 고점 대비 0.0% (건강한 상승)"
    ],
    "prev_regime": "강세",
    "regime_changed": false,
    "updated": "2026-04-25T02:48:00.385899"
  },
  {
    "regime": "강세",
    "score": 10,
    "strategy": "강세장_전략",
    "kospi_current": 6475.81,
    "kospi_ma20": 5805.0,
    "kospi_drawdown": 0.0,
    "week_change": 4.58,
    "month_change": 19.07,
    "consecutive_days": 197,
    "details": [
      "✅ 코스피 단기 정배열",
      "✅ 코스피 장기 정배열",
      "✅ 코스피 20일선 위",
      "✅ 최근 5일 +4.6% 상승",
      "✅ 최근 20일 +19.1% 상승",
      "✅ VIX 낮음 (18.6) → 안정",
      "✅ 고점 대비 0.0% (건강한 상승)"
    ],
    "prev_regime": "강세",
    "regime_changed": false,
    "updated": "2026-04-25T03:18:52.361678"
  },
  {
    "regime": "강세",
    "score": 10,
    "strategy": "강세장_전략",
    "kospi_current": 6475.81,
    "kospi_ma20": 5805.0,
    "kospi_drawdown": 0.0,
    "week_change": 4.58,
    "month_change": 19.07,
    "consecutive_days": 198,
    "details": [
      "✅ 코스피 단기 정배열",
      "✅ 코스피 장기 정배열",
      "✅ 코스피 20일선 위",
      "✅ 최근 5일 +4.6% 상승",
      "✅ 최근 20일 +19.1% 상승",
      "✅ VIX 낮음 (18.5) → 안정",
      "✅ 고점 대비 0.0% (건강한 상승)"
    ],
    "prev_regime": "강세",
    "regime_changed": false,
    "updated": "2026-04-25T03:49:43.908528"
  },
  {
    "regime": "강세",
    "score": 10,
    "strategy": "강세장_전략",
    "kospi_current": 6475.81,
    "kospi_ma20": 5805.0,
    "kospi_drawdown": 0.0,
    "week_change": 4.58,
    "month_change": 19.07,
    "consecutive_days": 199,
    "details": [
      "✅ 코스피 단기 정배열",
      "✅ 코스피 장기 정배열",
      "✅ 코스피 20일선 위",
      "✅ 최근 5일 +4.6% 상승",
      "✅ 최근 20일 +19.1% 상승",
      "✅ VIX 낮음 (18.7) → 안정",
      "✅ 고점 대비 0.0% (건강한 상승)"
    ],
    "prev_regime": "강세",
    "regime_changed": false,
    "updated": "2026-04-25T08:11:08.455896"
  },
  {
    "regime": "강세",
    "score": 10,
    "strategy": "강세장_전략",
    "kospi_current": 6475.63,
    "kospi_ma20": 5856.84,
    "kospi_drawdown": -0.0,
    "week_change": 4.13,
    "month_change": 22.71,
    "consecutive_days": 199,
    "details": [
      "✅ 코스피 단기 정배열",
      "✅ 코스피 장기 정배열",
      "✅ 코스피 20일선 위",
      "✅ 최근 5일 +4.1% 상승",
      "✅ 최근 20일 +22.7% 상승",
      "✅ VIX 낮음 (18.7) → 안정",
      "✅ 고점 대비 -0.0% (건강한 상승)"
    ],
    "prev_regime": "강세",
    "regime_changed": false,
    "updated": "2026-04-25T09:24:58.428137"
  },
  {
    "regime": "강세",
    "score": 10,
    "strategy": "강세장_전략",
    "kospi_current": 6475.63,
    "kospi_ma20": 5856.84,
    "kospi_drawdown": -0.0,
    "week_change": 4.13,
    "month_change": 22.71,
    "consecutive_days": 200,
    "details": [
      "✅ 코스피 단기 정배열",
      "✅ 코스피 장기 정배열",
      "✅ 코스피 20일선 위",
      "✅ 최근 5일 +4.1% 상승",
      "✅ 최근 20일 +22.7% 상승",
      "✅ VIX 낮음 (18.7) → 안정",
      "✅ 고점 대비 -0.0% (건강한 상승)"
    ],
    "prev_regime": "강세",
    "regime_changed": false,
    "updated": "2026-04-25T09:55:53.608324"
  },
  {
    "regime": "강세",
    "score": 10,
    "strategy": "강세장_전략",
    "kospi_current": 6475.63,
    "kospi_ma20": 5856.84,
    "kospi_drawdown": -0.0,
    "week_change": 4.13,
    "month_change": 22.71,
    "consecutive_days": 201,
    "details": [
      "✅ 코스피 단기 정배열",
      "✅ 코스피 장기 정배열",
      "✅ 코스피 20일선 위",
      "✅ 최근 5일 +4.1% 상승",
      "✅ 최근 20일 +22.7% 상승",
      "✅ VIX 낮음 (18.7) → 안정",
      "✅ 고점 대비 -0.0% (건강한 상승)"
    ],
    "prev_regime": "강세",
    "regime_changed": false,
    "updated": "2026-04-25T10:26:50.663270"
  },
  {
    "regime": "강세",
    "score": 10,
    "strategy": "강세장_전략",
    "kospi_current": 6475.63,
    "kospi_ma20": 5856.84,
    "kospi_drawdown": -0.0,
    "week_change": 4.13,
    "month_change": 22.71,
    "consecutive_days": 202,
    "details": [
      "✅ 코스피 단기 정배열",
      "✅ 코스피 장기 정배열",
      "✅ 코스피 20일선 위",
      "✅ 최근 5일 +4.1% 상승",
      "✅ 최근 20일 +22.7% 상승",
      "✅ VIX 낮음 (18.7) → 안정",
      "✅ 고점 대비 -0.0% (건강한 상승)"
    ],
    "prev_regime": "강세",
    "regime_changed": false,
    "updated": "2026-04-25T10:57:37.981135"
  },
  {
    "regime": "강세",
    "score": 10,
    "strategy": "강세장_전략",
    "kospi_current": 6475.63,
    "kospi_ma20": 5856.84,
    "kospi_drawdown": -0.0,
    "week_change": 4.13,
    "month_change": 22.71,
    "consecutive_days": 203,
    "details": [
      "✅ 코스피 단기 정배열",
      "✅ 코스피 장기 정배열",
      "✅ 코스피 20일선 위",
      "✅ 최근 5일 +4.1% 상승",
      "✅ 최근 20일 +22.7% 상승",
      "✅ VIX 낮음 (18.7) → 안정",
      "✅ 고점 대비 -0.0% (건강한 상승)"
    ],
    "prev_regime": "강세",
    "regime_changed": false,
    "updated": "2026-04-25T11:28:28.897863"
  },
  {
    "regime": "강세",
    "score": 10,
    "strategy": "강세장_전략",
    "kospi_current": 6475.63,
    "kospi_ma20": 5856.84,
    "kospi_drawdown": -0.0,
    "week_change": 4.13,
    "month_change": 22.71,
    "consecutive_days": 204,
    "details": [
      "✅ 코스피 단기 정배열",
      "✅ 코스피 장기 정배열",
      "✅ 코스피 20일선 위",
      "✅ 최근 5일 +4.1% 상승",
      "✅ 최근 20일 +22.7% 상승",
      "✅ VIX 낮음 (18.7) → 안정",
      "✅ 고점 대비 -0.0% (건강한 상승)"
    ],
    "prev_regime": "강세",
    "regime_changed": false,
    "updated": "2026-04-25T11:59:19.773632"
  },
  {
    "regime": "강세",
    "score": 10,
    "strategy": "강세장_전략",
    "kospi_current": 6475.63,
    "kospi_ma20": 5856.84,
    "kospi_drawdown": -0.0,
    "week_change": 4.13,
    "month_change": 22.71,
    "consecutive_days": 205,
    "details": [
      "✅ 코스피 단기 정배열",
      "✅ 코스피 장기 정배열",
      "✅ 코스피 20일선 위",
      "✅ 최근 5일 +4.1% 상승",
      "✅ 최근 20일 +22.7% 상승",
      "✅ VIX 낮음 (18.7) → 안정",
      "✅ 고점 대비 -0.0% (건강한 상승)"
    ],
    "prev_regime": "강세",
    "regime_changed": false,
    "updated": "2026-04-25T12:30:09.705690"
  },
  {
    "regime": "강세",
    "score": 10,
    "strategy": "강세장_전략",
    "kospi_current": 6475.63,
    "kospi_ma20": 5856.84,
    "kospi_drawdown": -0.0,
    "week_change": 4.13,
    "month_change": 22.71,
    "consecutive_days": 206,
    "details": [
      "✅ 코스피 단기 정배열",
      "✅ 코스피 장기 정배열",
      "✅ 코스피 20일선 위",
      "✅ 최근 5일 +4.1% 상승",
      "✅ 최근 20일 +22.7% 상승",
      "✅ VIX 낮음 (18.7) → 안정",
      "✅ 고점 대비 -0.0% (건강한 상승)"
    ],
    "prev_regime": "강세",
    "regime_changed": false,
    "updated": "2026-04-25T13:01:55.986359"
  },
  {
    "regime": "강세",
    "score": 10,
    "strategy": "강세장_전략",
    "kospi_current": 6475.63,
    "kospi_ma20": 5856.84,
    "kospi_drawdown": -0.0,
    "week_change": 4.13,
    "month_change": 22.71,
    "consecutive_days": 207,
    "details": [
      "✅ 코스피 단기 정배열",
      "✅ 코스피 장기 정배열",
      "✅ 코스피 20일선 위",
      "✅ 최근 5일 +4.1% 상승",
      "✅ 최근 20일 +22.7% 상승",
      "✅ VIX 낮음 (18.7) → 안정",
      "✅ 고점 대비 -0.0% (건강한 상승)"
    ],
    "prev_regime": "강세",
    "regime_changed": false,
    "updated": "2026-04-25T13:32:43.399517"
  },
  {
    "regime": "강세",
    "score": 10,
    "strategy": "강세장_전략",
    "kospi_current": 6475.63,
    "kospi_ma20": 5856.84,
    "kospi_drawdown": -0.0,
    "week_change": 4.13,
    "month_change": 22.71,
    "consecutive_days": 208,
    "details": [
      "✅ 코스피 단기 정배열",
      "✅ 코스피 장기 정배열",
      "✅ 코스피 20일선 위",
      "✅ 최근 5일 +4.1% 상승",
      "✅ 최근 20일 +22.7% 상승",
      "✅ VIX 낮음 (18.7) → 안정",
      "✅ 고점 대비 -0.0% (건강한 상승)"
    ],
    "prev_regime": "강세",
    "regime_changed": false,
    "updated": "2026-04-25T14:03:31.562520"
  },
  {
    "regime": "강세",
    "score": 10,
    "strategy": "강세장_전략",
    "kospi_current": 6475.63,
    "kospi_ma20": 5856.84,
    "kospi_drawdown": -0.0,
    "week_change": 4.13,
    "month_change": 22.71,
    "consecutive_days": 209,
    "details": [
      "✅ 코스피 단기 정배열",
      "✅ 코스피 장기 정배열",
      "✅ 코스피 20일선 위",
      "✅ 최근 5일 +4.1% 상승",
      "✅ 최근 20일 +22.7% 상승",
      "✅ VIX 낮음 (18.7) → 안정",
      "✅ 고점 대비 -0.0% (건강한 상승)"
    ],
    "prev_regime": "강세",
    "regime_changed": false,
    "updated": "2026-04-25T14:09:06.128663"
  },
  {
    "regime": "강세",
    "score": 10,
    "strategy": "강세장_전략",
    "kospi_current": 6475.63,
    "kospi_ma20": 5856.84,
    "kospi_drawdown": -0.0,
    "week_change": 4.13,
    "month_change": 22.71,
    "consecutive_days": 210,
    "details": [
      "✅ 코스피 단기 정배열",
      "✅ 코스피 장기 정배열",
      "✅ 코스피 20일선 위",
      "✅ 최근 5일 +4.1% 상승",
      "✅ 최근 20일 +22.7% 상승",
      "✅ VIX 낮음 (18.7) → 안정",
      "✅ 고점 대비 -0.0% (건강한 상승)"
    ],
    "prev_regime": "강세",
    "regime_changed": false,
    "updated": "2026-04-25T14:39:09.905514"
  },
  {
    "regime": "강세",
    "score": 10,
    "strategy": "강세장_전략",
    "kospi_current": 6475.63,
    "kospi_ma20": 5856.84,
    "kospi_drawdown": -0.0,
    "week_change": 4.13,
    "month_change": 22.71,
    "consecutive_days": 211,
    "details": [
      "✅ 코스피 단기 정배열",
      "✅ 코스피 장기 정배열",
      "✅ 코스피 20일선 위",
      "✅ 최근 5일 +4.1% 상승",
      "✅ 최근 20일 +22.7% 상승",
      "✅ VIX 낮음 (18.7) → 안정",
      "✅ 고점 대비 -0.0% (건강한 상승)"
    ],
    "prev_regime": "강세",
    "regime_changed": false,
    "updated": "2026-04-25T15:07:58.787333"
  },
  {
    "regime": "강세",
    "score": 10,
    "strategy": "강세장_전략",
    "kospi_current": 6475.63,
    "kospi_ma20": 5856.84,
    "kospi_drawdown": -0.0,
    "week_change": 4.13,
    "month_change": 22.71,
    "consecutive_days": 212,
    "details": [
      "✅ 코스피 단기 정배열",
      "✅ 코스피 장기 정배열",
      "✅ 코스피 20일선 위",
      "✅ 최근 5일 +4.1% 상승",
      "✅ 최근 20일 +22.7% 상승",
      "✅ VIX 낮음 (18.7) → 안정",
      "✅ 고점 대비 -0.0% (건강한 상승)"
    ],
    "prev_regime": "강세",
    "regime_changed": false,
    "updated": "2026-04-25T15:30:47.719915"
  },
  {
    "regime": "강세",
    "score": 10,
    "strategy": "강세장_전략",
    "kospi_current": 6475.63,
    "kospi_ma20": 5856.84,
    "kospi_drawdown": -0.0,
    "week_change": 4.13,
    "month_change": 22.71,
    "consecutive_days": 213,
    "details": [
      "✅ 코스피 단기 정배열",
      "✅ 코스피 장기 정배열",
      "✅ 코스피 20일선 위",
      "✅ 최근 5일 +4.1% 상승",
      "✅ 최근 20일 +22.7% 상승",
      "✅ VIX 낮음 (18.7) → 안정",
      "✅ 고점 대비 -0.0% (건강한 상승)"
    ],
    "prev_regime": "강세",
    "regime_changed": false,
    "updated": "2026-04-25T15:32:21.426487"
  },
  {
    "regime": "강세",
    "score": 10,
    "strategy": "강세장_전략",
    "kospi_current": 6475.63,
    "kospi_ma20": 5856.84,
    "kospi_drawdown": -0.0,
    "week_change": 4.13,
    "month_change": 22.71,
    "consecutive_days": 214,
    "details": [
      "✅ 코스피 단기 정배열",
      "✅ 코스피 장기 정배열",
      "✅ 코스피 20일선 위",
      "✅ 최근 5일 +4.1% 상승",
      "✅ 최근 20일 +22.7% 상승",
      "✅ VIX 낮음 (18.7) → 안정",
      "✅ 고점 대비 -0.0% (건강한 상승)"
    ],
    "prev_regime": "강세",
    "regime_changed": false,
    "updated": "2026-04-25T17:31:12.168193"
  },
  {
    "regime": "강세",
    "score": 10,
    "strategy": "강세장_전략",
    "kospi_current": 6475.63,
    "kospi_ma20": 5856.84,
    "kospi_drawdown": -0.0,
    "week_change": 4.13,
    "month_change": 22.71,
    "consecutive_days": 215,
    "details": [
      "✅ 코스피 단기 정배열",
      "✅ 코스피 장기 정배열",
      "✅ 코스피 20일선 위",
      "✅ 최근 5일 +4.1% 상승",
      "✅ 최근 20일 +22.7% 상승",
      "✅ VIX 낮음 (18.7) → 안정",
      "✅ 고점 대비 -0.0% (건강한 상승)"
    ],
    "prev_regime": "강세",
    "regime_changed": false,
    "updated": "2026-04-25T17:32:38.392794"
  },
  {
    "regime": "강세",
    "score": 10,
    "strategy": "강세장_전략",
    "kospi_current": 6475.63,
    "kospi_ma20": 5856.84,
    "kospi_drawdown": -0.0,
    "week_change": 4.13,
    "month_change": 22.71,
    "consecutive_days": 216,
    "details": [
      "✅ 코스피 단기 정배열",
      "✅ 코스피 장기 정배열",
      "✅ 코스피 20일선 위",
      "✅ 최근 5일 +4.1% 상승",
      "✅ 최근 20일 +22.7% 상승",
      "✅ VIX 낮음 (18.7) → 안정",
      "✅ 고점 대비 -0.0% (건강한 상승)"
    ],
    "prev_regime": "강세",
    "regime_changed": false,
    "updated": "2026-04-25T17:35:46.407464"
  },
  {
    "regime": "강세",
    "score": 10,
    "strategy": "강세장_전략",
    "kospi_current": 6475.63,
    "kospi_ma20": 5856.84,
    "kospi_drawdown": -0.0,
    "week_change": 4.13,
    "month_change": 22.71,
    "consecutive_days": 217,
    "details": [
      "✅ 코스피 단기 정배열",
      "✅ 코스피 장기 정배열",
      "✅ 코스피 20일선 위",
      "✅ 최근 5일 +4.1% 상승",
      "✅ 최근 20일 +22.7% 상승",
      "✅ VIX 낮음 (18.7) → 안정",
      "✅ 고점 대비 -0.0% (건강한 상승)"
    ],
    "prev_regime": "강세",
    "regime_changed": false,
    "updated": "2026-04-25T17:38:31.121959"
  },
  {
    "regime": "강세",
    "score": 10,
    "strategy": "강세장_전략",
    "kospi_current": 6475.63,
    "kospi_ma20": 5856.84,
    "kospi_drawdown": -0.0,
    "week_change": 4.13,
    "month_change": 22.71,
    "consecutive_days": 218,
    "details": [
      "✅ 코스피 단기 정배열",
      "✅ 코스피 장기 정배열",
      "✅ 코스피 20일선 위",
      "✅ 최근 5일 +4.1% 상승",
      "✅ 최근 20일 +22.7% 상승",
      "✅ VIX 낮음 (18.7) → 안정",
      "✅ 고점 대비 -0.0% (건강한 상승)"
    ],
    "prev_regime": "강세",
    "regime_changed": false,
    "updated": "2026-04-25T17:43:03.736344"
  },
  {
    "regime": "강세",
    "score": 10,
    "strategy": "강세장_전략",
    "kospi_current": 6475.63,
    "kospi_ma20": 5856.84,
    "kospi_drawdown": -0.0,
    "week_change": 4.13,
    "month_change": 22.71,
    "consecutive_days": 219,
    "details": [
      "✅ 코스피 단기 정배열",
      "✅ 코스피 장기 정배열",
      "✅ 코스피 20일선 위",
      "✅ 최근 5일 +4.1% 상승",
      "✅ 최근 20일 +22.7% 상승",
      "✅ VIX 낮음 (18.7) → 안정",
      "✅ 고점 대비 -0.0% (건강한 상승)"
    ],
    "prev_regime": "강세",
    "regime_changed": false,
    "updated": "2026-04-25T17:53:18.781937"
  },
  {
    "regime": "강세",
    "score": 10,
    "strategy": "강세장_전략",
    "kospi_current": 6475.63,
    "kospi_ma20": 5856.84,
    "kospi_drawdown": -0.0,
    "week_change": 4.13,
    "month_change": 22.71,
    "consecutive_days": 220,
    "details": [
      "✅ 코스피 단기 정배열",
      "✅ 코스피 장기 정배열",
      "✅ 코스피 20일선 위",
      "✅ 최근 5일 +4.1% 상승",
      "✅ 최근 20일 +22.7% 상승",
      "✅ VIX 낮음 (18.7) → 안정",
      "✅ 고점 대비 -0.0% (건강한 상승)"
    ],
    "prev_regime": "강세",
    "regime_changed": false,
    "updated": "2026-04-25T17:53:31.401833"
  },
  {
    "regime": "강세",
    "score": 10,
    "strategy": "강세장_전략",
    "kospi_current": 6475.63,
    "kospi_ma20": 5856.84,
    "kospi_drawdown": -0.0,
    "week_change": 4.13,
    "month_change": 22.71,
    "consecutive_days": 221,
    "details": [
      "✅ 코스피 단기 정배열",
      "✅ 코스피 장기 정배열",
      "✅ 코스피 20일선 위",
      "✅ 최근 5일 +4.1% 상승",
      "✅ 최근 20일 +22.7% 상승",
      "✅ VIX 낮음 (18.7) → 안정",
      "✅ 고점 대비 -0.0% (건강한 상승)"
    ],
    "prev_regime": "강세",
    "regime_changed": false,
    "updated": "2026-04-25T18:12:37.793871"
  },
  {
    "regime": "강세",
    "score": 10,
    "strategy": "강세장_전략",
    "kospi_current": 6475.63,
    "kospi_ma20": 5856.84,
    "kospi_drawdown": -0.0,
    "week_change": 4.13,
    "month_change": 22.71,
    "consecutive_days": 222,
    "details": [
      "✅ 코스피 단기 정배열",
      "✅ 코스피 장기 정배열",
      "✅ 코스피 20일선 위",
      "✅ 최근 5일 +4.1% 상승",
      "✅ 최근 20일 +22.7% 상승",
      "✅ VIX 낮음 (18.7) → 안정",
      "✅ 고점 대비 -0.0% (건강한 상승)"
    ],
    "prev_regime": "강세",
    "regime_changed": false,
    "updated": "2026-04-25T18:12:47.307425"
  },
  {
    "regime": "강세",
    "score": 10,
    "strategy": "강세장_전략",
    "kospi_current": 6475.63,
    "kospi_ma20": 5856.84,
    "kospi_drawdown": -0.0,
    "week_change": 4.13,
    "month_change": 22.71,
    "consecutive_days": 223,
    "details": [
      "✅ 코스피 단기 정배열",
      "✅ 코스피 장기 정배열",
      "✅ 코스피 20일선 위",
      "✅ 최근 5일 +4.1% 상승",
      "✅ 최근 20일 +22.7% 상승",
      "✅ VIX 낮음 (18.7) → 안정",
      "✅ 고점 대비 -0.0% (건강한 상승)"
    ],
    "prev_regime": "강세",
    "regime_changed": false,
    "updated": "2026-04-25T18:14:37.689360"
  },
  {
    "regime": "강세",
    "score": 10,
    "strategy": "강세장_전략",
    "kospi_current": 6475.63,
    "kospi_ma20": 5856.84,
    "kospi_drawdown": -0.0,
    "week_change": 4.13,
    "month_change": 22.71,
    "consecutive_days": 224,
    "details": [
      "✅ 코스피 단기 정배열",
      "✅ 코스피 장기 정배열",
      "✅ 코스피 20일선 위",
      "✅ 최근 5일 +4.1% 상승",
      "✅ 최근 20일 +22.7% 상승",
      "✅ VIX 낮음 (18.7) → 안정",
      "✅ 고점 대비 -0.0% (건강한 상승)"
    ],
    "prev_regime": "강세",
    "regime_changed": false,
    "updated": "2026-04-25T18:20:35.297098"
  },
  {
    "regime": "강세",
    "score": 10,
    "strategy": "강세장_전략",
    "kospi_current": 6475.63,
    "kospi_ma20": 5856.84,
    "kospi_drawdown": -0.0,
    "week_change": 4.13,
    "month_change": 22.71,
    "consecutive_days": 225,
    "details": [
      "✅ 코스피 단기 정배열",
      "✅ 코스피 장기 정배열",
      "✅ 코스피 20일선 위",
      "✅ 최근 5일 +4.1% 상승",
      "✅ 최근 20일 +22.7% 상승",
      "✅ VIX 낮음 (18.7) → 안정",
      "✅ 고점 대비 -0.0% (건강한 상승)"
    ],
    "prev_regime": "강세",
    "regime_changed": false,
    "updated": "2026-04-25T18:21:23.615673"
  },
  {
    "regime": "강세",
    "score": 10,
    "strategy": "강세장_전략",
    "kospi_current": 6475.63,
    "kospi_ma20": 5856.84,
    "kospi_drawdown": -0.0,
    "week_change": 4.13,
    "month_change": 22.71,
    "consecutive_days": 226,
    "details": [
      "✅ 코스피 단기 정배열",
      "✅ 코스피 장기 정배열",
      "✅ 코스피 20일선 위",
      "✅ 최근 5일 +4.1% 상승",
      "✅ 최근 20일 +22.7% 상승",
      "✅ VIX 낮음 (18.7) → 안정",
      "✅ 고점 대비 -0.0% (건강한 상승)"
    ],
    "prev_regime": "강세",
    "regime_changed": false,
    "updated": "2026-04-25T21:22:59.824956"
  },
  {
    "regime": "강세",
    "score": 10,
    "strategy": "강세장_전략",
    "kospi_current": 6475.63,
    "kospi_ma20": 5856.84,
    "kospi_drawdown": -0.0,
    "week_change": 4.13,
    "month_change": 22.71,
    "consecutive_days": 227,
    "details": [
      "✅ 코스피 단기 정배열",
      "✅ 코스피 장기 정배열",
      "✅ 코스피 20일선 위",
      "✅ 최근 5일 +4.1% 상승",
      "✅ 최근 20일 +22.7% 상승",
      "✅ VIX 낮음 (18.7) → 안정",
      "✅ 고점 대비 -0.0% (건강한 상승)"
    ],
    "prev_regime": "강세",
    "regime_changed": false,
    "updated": "2026-04-25T21:54:11.022562"
  },
  {
    "regime": "강세",
    "score": 10,
    "strategy": "강세장_전략",
    "kospi_current": 6475.63,
    "kospi_ma20": 5856.84,
    "kospi_drawdown": -0.0,
    "week_change": 4.13,
    "month_change": 22.71,
    "consecutive_days": 228,
    "details": [
      "✅ 코스피 단기 정배열",
      "✅ 코스피 장기 정배열",
      "✅ 코스피 20일선 위",
      "✅ 최근 5일 +4.1% 상승",
      "✅ 최근 20일 +22.7% 상승",
      "✅ VIX 낮음 (18.7) → 안정",
      "✅ 고점 대비 -0.0% (건강한 상승)"
    ],
    "prev_regime": "강세",
    "regime_changed": false,
    "updated": "2026-04-25T22:25:13.863295"
  },
  {
    "regime": "강세",
    "score": 10,
    "strategy": "강세장_전략",
    "kospi_current": 6475.63,
    "kospi_ma20": 5856.84,
    "kospi_drawdown": -0.0,
    "week_change": 4.13,
    "month_change": 22.71,
    "consecutive_days": 229,
    "details": [
      "✅ 코스피 단기 정배열",
      "✅ 코스피 장기 정배열",
      "✅ 코스피 20일선 위",
      "✅ 최근 5일 +4.1% 상승",
      "✅ 최근 20일 +22.7% 상승",
      "✅ VIX 낮음 (18.7) → 안정",
      "✅ 고점 대비 -0.0% (건강한 상승)"
    ],
    "prev_regime": "강세",
    "regime_changed": false,
    "updated": "2026-04-25T22:34:10.030600"
  },
  {
    "regime": "강세",
    "score": 10,
    "strategy": "강세장_전략",
    "kospi_current": 6475.63,
    "kospi_ma20": 5856.84,
    "kospi_drawdown": -0.0,
    "week_change": 4.13,
    "month_change": 22.71,
    "consecutive_days": 230,
    "details": [
      "✅ 코스피 단기 정배열",
      "✅ 코스피 장기 정배열",
      "✅ 코스피 20일선 위",
      "✅ 최근 5일 +4.1% 상승",
      "✅ 최근 20일 +22.7% 상승",
      "✅ VIX 낮음 (18.7) → 안정",
      "✅ 고점 대비 -0.0% (건강한 상승)"
    ],
    "prev_regime": "강세",
    "regime_changed": false,
    "updated": "2026-04-25T22:34:35.317192"
  },
  {
    "regime": "강세",
    "score": 10,
    "strategy": "강세장_전략",
    "kospi_current": 6475.63,
    "kospi_ma20": 5856.84,
    "kospi_drawdown": -0.0,
    "week_change": 4.13,
    "month_change": 22.71,
    "consecutive_days": 231,
    "details": [
      "✅ 코스피 단기 정배열",
      "✅ 코스피 장기 정배열",
      "✅ 코스피 20일선 위",
      "✅ 최근 5일 +4.1% 상승",
      "✅ 최근 20일 +22.7% 상승",
      "✅ VIX 낮음 (18.7) → 안정",
      "✅ 고점 대비 -0.0% (건강한 상승)"
    ],
    "prev_regime": "강세",
    "regime_changed": false,
    "updated": "2026-04-25T22:42:34.690351"
  },
  {
    "regime": "강세",
    "score": 10,
    "strategy": "강세장_전략",
    "kospi_current": 6475.63,
    "kospi_ma20": 5856.84,
    "kospi_drawdown": -0.0,
    "week_change": 4.13,
    "month_change": 22.71,
    "consecutive_days": 232,
    "details": [
      "✅ 코스피 단기 정배열",
      "✅ 코스피 장기 정배열",
      "✅ 코스피 20일선 위",
      "✅ 최근 5일 +4.1% 상승",
      "✅ 최근 20일 +22.7% 상승",
      "✅ VIX 낮음 (18.7) → 안정",
      "✅ 고점 대비 -0.0% (건강한 상승)"
    ],
    "prev_regime": "강세",
    "regime_changed": false,
    "updated": "2026-04-25T22:49:50.900960"
  },
  {
    "regime": "강세",
    "score": 10,
    "strategy": "강세장_전략",
    "kospi_current": 6475.63,
    "kospi_ma20": 5856.84,
    "kospi_drawdown": -0.0,
    "week_change": 4.13,
    "month_change": 22.71,
    "consecutive_days": 233,
    "details": [
      "✅ 코스피 단기 정배열",
      "✅ 코스피 장기 정배열",
      "✅ 코스피 20일선 위",
      "✅ 최근 5일 +4.1% 상승",
      "✅ 최근 20일 +22.7% 상승",
      "✅ VIX 낮음 (18.7) → 안정",
      "✅ 고점 대비 -0.0% (건강한 상승)"
    ],
    "prev_regime": "강세",
    "regime_changed": false,
    "updated": "2026-04-25T22:53:25.736196"
  },
  {
    "regime": "강세",
    "score": 10,
    "strategy": "강세장_전략",
    "kospi_current": 6475.63,
    "kospi_ma20": 5856.84,
    "kospi_drawdown": -0.0,
    "week_change": 4.13,
    "month_change": 22.71,
    "consecutive_days": 234,
    "details": [
      "✅ 코스피 단기 정배열",
      "✅ 코스피 장기 정배열",
      "✅ 코스피 20일선 위",
      "✅ 최근 5일 +4.1% 상승",
      "✅ 최근 20일 +22.7% 상승",
      "✅ VIX 낮음 (18.7) → 안정",
      "✅ 고점 대비 -0.0% (건강한 상승)"
    ],
    "prev_regime": "강세",
    "regime_changed": false,
    "updated": "2026-04-25T23:01:43.779146"
  },
  {
    "regime": "강세",
    "score": 10,
    "strategy": "강세장_전략",
    "kospi_current": 6475.63,
    "kospi_ma20": 5856.84,
    "kospi_drawdown": -0.0,
    "week_change": 4.13,
    "month_change": 22.71,
    "consecutive_days": 235,
    "details": [
      "✅ 코스피 단기 정배열",
      "✅ 코스피 장기 정배열",
      "✅ 코스피 20일선 위",
      "✅ 최근 5일 +4.1% 상승",
      "✅ 최근 20일 +22.7% 상승",
      "✅ VIX 낮음 (18.7) → 안정",
      "✅ 고점 대비 -0.0% (건강한 상승)"
    ],
    "prev_regime": "강세",
    "regime_changed": false,
    "updated": "2026-04-25T23:02:22.051585"
  },
  {
    "regime": "강세",
    "score": 10,
    "strategy": "강세장_전략",
    "kospi_current": 6475.63,
    "kospi_ma20": 5856.84,
    "kospi_drawdown": -0.0,
    "week_change": 4.13,
    "month_change": 22.71,
    "consecutive_days": 236,
    "details": [
      "✅ 코스피 단기 정배열",
      "✅ 코스피 장기 정배열",
      "✅ 코스피 20일선 위",
      "✅ 최근 5일 +4.1% 상승",
      "✅ 최근 20일 +22.7% 상승",
      "✅ VIX 낮음 (18.7) → 안정",
      "✅ 고점 대비 -0.0% (건강한 상승)"
    ],
    "prev_regime": "강세",
    "regime_changed": false,
    "updated": "2026-04-25T23:03:16.740314"
  },
  {
    "regime": "강세",
    "score": 10,
    "strategy": "강세장_전략",
    "kospi_current": 6475.63,
    "kospi_ma20": 5856.84,
    "kospi_drawdown": -0.0,
    "week_change": 4.13,
    "month_change": 22.71,
    "consecutive_days": 237,
    "details": [
      "✅ 코스피 단기 정배열",
      "✅ 코스피 장기 정배열",
      "✅ 코스피 20일선 위",
      "✅ 최근 5일 +4.1% 상승",
      "✅ 최근 20일 +22.7% 상승",
      "✅ VIX 낮음 (18.7) → 안정",
      "✅ 고점 대비 -0.0% (건강한 상승)"
    ],
    "prev_regime": "강세",
    "regime_changed": false,
    "updated": "2026-04-25T23:09:05.892240"
  },
  {
    "regime": "강세",
    "score": 10,
    "strategy": "강세장_전략",
    "kospi_current": 6475.63,
    "kospi_ma20": 5856.84,
    "kospi_drawdown": -0.0,
    "week_change": 4.13,
    "month_change": 22.71,
    "consecutive_days": 238,
    "details": [
      "✅ 코스피 단기 정배열",
      "✅ 코스피 장기 정배열",
      "✅ 코스피 20일선 위",
      "✅ 최근 5일 +4.1% 상승",
      "✅ 최근 20일 +22.7% 상승",
      "✅ VIX 낮음 (18.7) → 안정",
      "✅ 고점 대비 -0.0% (건강한 상승)"
    ],
    "prev_regime": "강세",
    "regime_changed": false,
    "updated": "2026-04-25T23:13:43.231518"
  },
  {
    "regime": "강세",
    "score": 10,
    "strategy": "강세장_전략",
    "kospi_current": 6475.63,
    "kospi_ma20": 5856.84,
    "kospi_drawdown": -0.0,
    "week_change": 4.13,
    "month_change": 22.71,
    "consecutive_days": 239,
    "details": [
      "✅ 코스피 단기 정배열",
      "✅ 코스피 장기 정배열",
      "✅ 코스피 20일선 위",
      "✅ 최근 5일 +4.1% 상승",
      "✅ 최근 20일 +22.7% 상승",
      "✅ VIX 낮음 (18.7) → 안정",
      "✅ 고점 대비 -0.0% (건강한 상승)"
    ],
    "prev_regime": "강세",
    "regime_changed": false,
    "updated": "2026-04-25T23:14:47.208651"
  },
  {
    "regime": "강세",
    "score": 10,
    "strategy": "강세장_전략",
    "kospi_current": 6475.63,
    "kospi_ma20": 5856.84,
    "kospi_drawdown": -0.0,
    "week_change": 4.13,
    "month_change": 22.71,
    "consecutive_days": 240,
    "details": [
      "✅ 코스피 단기 정배열",
      "✅ 코스피 장기 정배열",
      "✅ 코스피 20일선 위",
      "✅ 최근 5일 +4.1% 상승",
      "✅ 최근 20일 +22.7% 상승",
      "✅ VIX 낮음 (18.7) → 안정",
      "✅ 고점 대비 -0.0% (건강한 상승)"
    ],
    "prev_regime": "강세",
    "regime_changed": false,
    "updated": "2026-04-25T23:34:07.590163"
  },
  {
    "regime": "강세",
    "score": 10,
    "strategy": "강세장_전략",
    "kospi_current": 6475.63,
    "kospi_ma20": 5856.84,
    "kospi_drawdown": -0.0,
    "week_change": 4.13,
    "month_change": 22.71,
    "consecutive_days": 241,
    "details": [
      "✅ 코스피 단기 정배열",
      "✅ 코스피 장기 정배열",
      "✅ 코스피 20일선 위",
      "✅ 최근 5일 +4.1% 상승",
      "✅ 최근 20일 +22.7% 상승",
      "✅ VIX 낮음 (18.7) → 안정",
      "✅ 고점 대비 -0.0% (건강한 상승)"
    ],
    "prev_regime": "강세",
    "regime_changed": false,
    "updated": "2026-04-26T04:05:20.607524"
  },
  {
    "regime": "강세",
    "score": 10,
    "strategy": "강세장_전략",
    "kospi_current": 6475.63,
    "kospi_ma20": 5856.84,
    "kospi_drawdown": -0.0,
    "week_change": 4.13,
    "month_change": 22.71,
    "consecutive_days": 242,
    "details": [
      "✅ 코스피 단기 정배열",
      "✅ 코스피 장기 정배열",
      "✅ 코스피 20일선 위",
      "✅ 최근 5일 +4.1% 상승",
      "✅ 최근 20일 +22.7% 상승",
      "✅ VIX 낮음 (18.7) → 안정",
      "✅ 고점 대비 -0.0% (건강한 상승)"
    ],
    "prev_regime": "강세",
    "regime_changed": false,
    "updated": "2026-04-26T04:33:22.483194"
  },
  {
    "regime": "강세",
    "score": 10,
    "strategy": "강세장_전략",
    "kospi_current": 6475.63,
    "kospi_ma20": 5856.84,
    "kospi_drawdown": -0.0,
    "week_change": 4.13,
    "month_change": 22.71,
    "consecutive_days": 243,
    "details": [
      "✅ 코스피 단기 정배열",
      "✅ 코스피 장기 정배열",
      "✅ 코스피 20일선 위",
      "✅ 최근 5일 +4.1% 상승",
      "✅ 최근 20일 +22.7% 상승",
      "✅ VIX 낮음 (18.7) → 안정",
      "✅ 고점 대비 -0.0% (건강한 상승)"
    ],
    "prev_regime": "강세",
    "regime_changed": false,
    "updated": "2026-04-26T04:47:18.614467"
  },
  {
    "regime": "강세",
    "score": 10,
    "strategy": "강세장_전략",
    "kospi_current": 6475.63,
    "kospi_ma20": 5856.84,
    "kospi_drawdown": -0.0,
    "week_change": 4.13,
    "month_change": 22.71,
    "consecutive_days": 244,
    "details": [
      "✅ 코스피 단기 정배열",
      "✅ 코스피 장기 정배열",
      "✅ 코스피 20일선 위",
      "✅ 최근 5일 +4.1% 상승",
      "✅ 최근 20일 +22.7% 상승",
      "✅ VIX 낮음 (18.7) → 안정",
      "✅ 고점 대비 -0.0% (건강한 상승)"
    ],
    "prev_regime": "강세",
    "regime_changed": false,
    "updated": "2026-04-26T05:37:16.708737"
  },
  {
    "regime": "강세",
    "score": 10,
    "strategy": "강세장_전략",
    "kospi_current": 6475.63,
    "kospi_ma20": 5856.84,
    "kospi_drawdown": -0.0,
    "week_change": 4.13,
    "month_change": 22.71,
    "consecutive_days": 245,
    "details": [
      "✅ 코스피 단기 정배열",
      "✅ 코스피 장기 정배열",
      "✅ 코스피 20일선 위",
      "✅ 최근 5일 +4.1% 상승",
      "✅ 최근 20일 +22.7% 상승",
      "✅ VIX 낮음 (18.7) → 안정",
      "✅ 고점 대비 -0.0% (건강한 상승)"
    ],
    "prev_regime": "강세",
    "regime_changed": false,
    "updated": "2026-04-26T05:39:03.188024"
  }
]